moodlexport/__init__.py
moodlexport/python_to_moodle.py
moodlexport/tex_to_python.py
moodlexport-0.0.1.dist-info/LICENSE.txt
moodlexport-0.0.1.dist-info/METADATA
moodlexport-0.0.1.dist-info/WHEEL
moodlexport-0.0.1.dist-info/top_level.txt
moodlexport-0.0.1.dist-info/RECORD
