Metadata-Version: 2.1
Name: moodlexport
Version: 0.0.1
Summary: A package to export test questions into Moodle from python or latex
Home-page: https://github.com/Guillaume-Garrigos/moodlexport
Author: Guillaume Garrigos
Author-email: guillaume.garrigos@lpsm.paris
License: UNKNOWN
Platform: UNKNOWN
Classifier: Programming Language :: Python :: 3
Classifier: License :: OSI Approved :: MIT License
Classifier: Operating System :: OS Independent
Requires-Python: >=3.7
